streamlit_labelstudio/__init__.py
streamlit_labelstudio/frontend/build/asset-manifest.json
streamlit_labelstudio/frontend/build/bootstrap.min.css
streamlit_labelstudio/frontend/build/index.html
streamlit_labelstudio/frontend/build/precache-manifest.80b96469db7513a745e8ff5f01aaab33.js
streamlit_labelstudio/frontend/build/service-worker.js
streamlit_labelstudio/frontend/build/static/css/2.b789f26a.chunk.css
streamlit_labelstudio/frontend/build/static/css/2.b789f26a.chunk.css.map
streamlit_labelstudio/frontend/build/static/js/2.d173a6f3.chunk.js
streamlit_labelstudio/frontend/build/static/js/2.d173a6f3.chunk.js.LICENSE.txt
streamlit_labelstudio/frontend/build/static/js/2.d173a6f3.chunk.js.map
streamlit_labelstudio/frontend/build/static/js/main.26a52596.chunk.js
streamlit_labelstudio/frontend/build/static/js/main.26a52596.chunk.js.map
streamlit_labelstudio/frontend/build/static/js/runtime-main.7e58624a.js
streamlit_labelstudio/frontend/build/static/js/runtime-main.7e58624a.js.map
streamlit_labelstudio-0.0.3.dist-info/LICENSE
streamlit_labelstudio-0.0.3.dist-info/METADATA
streamlit_labelstudio-0.0.3.dist-info/WHEEL
streamlit_labelstudio-0.0.3.dist-info/top_level.txt
streamlit_labelstudio-0.0.3.dist-info/RECORD
