Metadata-Version: 2.1
Name: streamlit-labelstudio
Version: 0.0.3
Summary: A Streamlit component that provides an annotation interface using the LabelStudio Frontend
Home-page: https://github.com/deneland/streamlit-labelstudio
Author: 
Author-email: 
License: UNKNOWN
Platform: UNKNOWN
Requires-Python: >=3.6
Requires-Dist: streamlit (>=0.63)
